inne/__init__.py
inne/_inne.py
inne/_version.py
inne/tests/__init__.py
inne/tests/test_common.py
inne/tests/test_inne.py
inne-0.2.0.dist-info/LICENSE
inne-0.2.0.dist-info/METADATA
inne-0.2.0.dist-info/WHEEL
inne-0.2.0.dist-info/top_level.txt
inne-0.2.0.dist-info/RECORD
